{"p2iDMorhCM2G5vEOSad2pA==":"meet-1837x1217.png","OM6hTwqMAQpTVhLcPG86xg==":"background1.jpg","//OuKQl70Rw0z4LIE4kGnA==":"wallpaper-black-beauty-bronze-glamour-style-black-girl-1920x1288.jpg","WH7zMK2bQnnL012c8oPU7g==":"ener-1368x1264.png","9FtR2m8ek1mKnXcCI5U60w==":"register-now-1400x762.png","+92qBmiLyBxCs7M2hb6lug==":"closed-1400x700.png","8zIEAx61pjU36ppNwGZK9w==":"innovate%20trans-295x128.png","lWp1cqpfjkUa+dIda3a1nw==":"wallpaper-black-beauty-bronze-glamour-style-black-girl-1-2000x1341.jpg"}